httpspyserver/__init__.py
httpspyserver/__main__.py
httpspyserver/server.py
httpspyserver-0.4.0.dist-info/entry_points.txt
httpspyserver-0.4.0.dist-info/licenses/LICENSE
httpspyserver-0.4.0.dist-info/WHEEL
httpspyserver-0.4.0.dist-info/METADATA
httpspyserver-0.4.0.dist-info/RECORD
