Metadata-Version: 2.4
Name: httpspyserver
Version: 0.4.0
Summary: Minimal HTTPS server using only Python's standard library.
Keywords: https,ssl,server,python,cli
Author-email: therationalconspiracist <idndteog19@gmail.com>
Requires-Python: >=3.7
Classifier: Programming Language :: Python :: 3
Classifier: License :: OSI Approved :: MIT License
Classifier: Operating System :: OS Independent
Classifier: Topic :: Internet :: WWW/HTTP :: HTTP Servers
License-File: LICENSE
